python4DBI/python4DBI.py
python4DBI-1.0.0.dist-info/LICENSE
python4DBI-1.0.0.dist-info/METADATA
python4DBI-1.0.0.dist-info/WHEEL
python4DBI-1.0.0.dist-info/top_level.txt
python4DBI-1.0.0.dist-info/RECORD
