Metadata-Version: 2.1
Name: python4DBI
Version: 1.0.0
Summary: The python 4DBI
Home-page: https://gitlab.com/marcianobarros/python4dbi
Author: Marciano Barros
Author-email: marciano.barros@pestana.com
License: MIT
Keywords: datababase drivers DBI 4d
Platform: UNKNOWN
Classifier: License :: OSI Approved :: MIT License
Classifier: Programming Language :: Python :: 3
Classifier: Topic :: Database
Classifier: Intended Audience :: Developers
Classifier: Development Status :: 5 - Production/Stable
Requires-Dist: texttable
